oagi/__init__.py
oagi/constants.py
oagi/exceptions.py
oagi/logging.py
oagi/actor/__init__.py
oagi/actor/async_.py
oagi/actor/async_short.py
oagi/actor/base.py
oagi/actor/short.py
oagi/actor/sync.py
oagi/agent/__init__.py
oagi/agent/default.py
oagi/agent/factories.py
oagi/agent/protocol.py
oagi/agent/registry.py
oagi/agent/observer/__init__.py
oagi/agent/observer/agent_observer.py
oagi/agent/observer/events.py
oagi/agent/observer/exporters.py
oagi/agent/observer/protocol.py
oagi/agent/observer/report_template.html
oagi/agent/tasker/__init__.py
oagi/agent/tasker/memory.py
oagi/agent/tasker/models.py
oagi/agent/tasker/planner.py
oagi/agent/tasker/taskee_agent.py
oagi/agent/tasker/tasker_agent.py
oagi/cli/__init__.py
oagi/cli/agent.py
oagi/cli/display.py
oagi/cli/main.py
oagi/cli/server.py
oagi/cli/tracking.py
oagi/cli/utils.py
oagi/client/__init__.py
oagi/client/async_.py
oagi/client/base.py
oagi/client/sync.py
oagi/handler/__init__.py
oagi/handler/_macos.py
oagi/handler/_windows.py
oagi/handler/async_pyautogui_action_handler.py
oagi/handler/async_screenshot_maker.py
oagi/handler/capslock_manager.py
oagi/handler/pil_image.py
oagi/handler/pyautogui_action_handler.py
oagi/handler/screenshot_maker.py
oagi/handler/utils.py
oagi/server/__init__.py
oagi/server/agent_wrappers.py
oagi/server/config.py
oagi/server/main.py
oagi/server/models.py
oagi/server/session_store.py
oagi/server/socketio_server.py
oagi/task/__init__.py
oagi/types/__init__.py
oagi/types/action_handler.py
oagi/types/async_action_handler.py
oagi/types/async_image_provider.py
oagi/types/image.py
oagi/types/image_provider.py
oagi/types/step_observer.py
oagi/types/url.py
oagi/types/models/__init__.py
oagi/types/models/action.py
oagi/types/models/client.py
oagi/types/models/image_config.py
oagi/types/models/step.py
oagi/utils/__init__.py
oagi/utils/output_parser.py
oagi/utils/prompt_builder.py
oagi_core-0.12.1.dist-info/METADATA
oagi_core-0.12.1.dist-info/WHEEL
oagi_core-0.12.1.dist-info/entry_points.txt
oagi_core-0.12.1.dist-info/licenses/LICENSE
oagi_core-0.12.1.dist-info/RECORD
