Metadata-Version: 2.3
Name: oagi-core
Version: 0.12.1
Summary: Official API of OpenAGI Foundation
Project-URL: Homepage, https://github.com/agiopen-org/oagi
Author-email: OpenAGI Foundation <contact@agiopen.org>
License: MIT License
Requires-Python: >=3.10
Requires-Dist: httpx>=0.24.0
Requires-Dist: openai>=1.3.0
Requires-Dist: pydantic>=2.0.0
Requires-Dist: rich>=10.0.0
Provides-Extra: desktop
Requires-Dist: pillow>=9.0.0; extra == 'desktop'
Requires-Dist: pyautogui>=0.9.54; extra == 'desktop'
Requires-Dist: pyobjc-framework-applicationservices>=8.0; (sys_platform == 'darwin') and extra == 'desktop'
Requires-Dist: pyobjc-framework-quartz>=8.0; (sys_platform == 'darwin') and extra == 'desktop'
Provides-Extra: server
Requires-Dist: fastapi[standard]>=0.100.0; extra == 'server'
Requires-Dist: pydantic-settings>=2.0.0; extra == 'server'
Requires-Dist: python-socketio>=5.5.0; extra == 'server'
Requires-Dist: uvicorn[standard]>=0.20.0; extra == 'server'
